SIST02_converter/SIST02_convert_URL.py
SIST02_converter/__init__.py
SIST02_converter-0.1.6.dist-info/METADATA
SIST02_converter-0.1.6.dist-info/WHEEL
SIST02_converter-0.1.6.dist-info/top_level.txt
SIST02_converter-0.1.6.dist-info/RECORD
