Metadata-Version: 2.1
Name: SIST02-converter
Version: 0.1.6
Summary: Conversion of input URL to SIST02 style.
Home-page: UNKNOWN
License: UNKNOWN
Platform: UNKNOWN
